{"id":551,"artist":"Reginaldo Rossi","title":"A Raposa e as Uvas","genero":"BREGA","src":"A_Raposa_A_Raposa_e_as_Uvas_Reginaldo-Rossi.m4a"},
    {"id":552,"artist":"Milionário e José Rico","title":"Brigas","genero":"BREGA","src":"Brigas-Brigas-MILIONARIO-JOSE-RICO-BREGA.m4a"},
    {"id":553,"artist":"Vontade","title":"Canteiros","genero":"BREGA","src":"CANTEIROS_Vontade_BREGA.m4a"},
    {"id":554,"artist":"Fernando Mendes","title":"Coisas Estranhas","genero":"BREGA","src":"Coisas_Estranhas_FERNANDO-MENDES-BREGA.m4a"},
    {"id":555,"artist":"Renato Blue Caps","title":"Com Você no Coração","genero":"BREGA","src":"COM-VC-NO-CORACAO-RENATO-BLUE-CAPS-BREGA.m4a"},
    {"id":556,"artist":"José Augusto","title":"De Que Vale Ter Tudo na Vida","genero":"BREGA","src":"De_Que_Vale_Ter_Tudo_Na_Vida_Jos_Augusto_BREGA.m4a"},
    {"id":557,"artist":"Dedim Gouveia","title":"Dedim Gouveia (Dupla)","genero":"BREGA","src":"Dedim_Gouveia_Dupla-BREGA.m4a"},
    {"id":558,"artist":"Abílio","title":"Entre Espumas","genero":"BREGA","src":"Entre_Espumas_ABILIO-BREGA.m4a"},
    {"id":559,"artist":"Lindomar Castilho","title":"Eu Vou Rifar Meu Coração","genero":"BREGA","src":"Lindomar_Castilho_Eu_Vou_Rifar_Meu_Cora_BREGA.m4a"},
    {"id":560,"artist":"Lindomar Castilho","title":"Feiticeira","genero":"BREGA","src":"Feiticeira_LINDOMAR-CAST_BREGA.m4a"},
    {"id":561,"artist":"Fernando Mendes","title":"Faz Mais","genero":"BREGA","src":"Fernando_Mendes_Faz_Mais_Faz_BREGA.m4a"},
    {"id":562,"artist":"Fernando Mendes","title":"Recordações","genero":"BREGA","src":"Fernando_Mendes_Recordacoes_BREGA.m4a"},
    {"id":563,"artist":"Madrugada Amiga","title":"Madrugada Amiga","genero":"BREGA","src":"Madrugada_Amiga_Madrugada_Amiga_BREGA.m4a"},
    {"id":564,"artist":"Odair José","title":"Mande Nem que Seja um Telegrama","genero":"BREGA","src":"ODAIR-JOSE-Mande_Nem_Que_Seja_um_Telegrama_B.m4a"},
    {"id":565,"artist":"Mano a Mano","title":"Pedindo Amor","genero":"BREGA","src":"MANO_A_MANO_Pedindo_Amor_B.m4a"},
    {"id":566,"artist":"Reginaldo Rossi","title":"Meu Fracasso","genero":"BREGA","src":"Meu_Fracasso_Meu_REGILDO-ROSSI-B.m4a"},
    {"id":567,"artist":"Altemar Dutra","title":"Meu Velho","genero":"BREGA","src":"MEU_VELHO-ALTEMAR-DUTRA-B.mp3"},
    {"id":568,"artist":"Raimundo Soldado","title":"Minha Garota","genero":"BREGA","src":"Minha_Garota_RAIMUNDO-SOLDADO-B.m4a"},
    {"id":569,"artist":"Vando","title":"Mordida na Maçã","genero":"BREGA","src":"Mordida_Na_Mordida_Na_Ma_VANDO-B.m4a"},
    {"id":570,"artist":"Na Hora do Adeus","title":"Na Hora do Adeus","genero":"BREGA","src":"Na_hora_Na_hora_do_adeus_B.m4a"},
    {"id":571,"artist":"Violão de Ouro","title":"Nosso Juramento","genero":"BREGA","src":"Nosso_Juramento_VIOLAO-DE-OURO-B.m4a"},
    {"id":572,"artist":"Violão de Ouro","title":"O Pranto","genero":"BREGA","src":"O_Pranto-VIOLAO-DE-OURO-B.m4a"},
    {"id":573,"artist":"Zezo Potiguar e Luan Estilizado","title":"O Vagabundo","genero":"BREGA","src":"O_Vagabundo_DVD_Vontade_Ra_Saia_Rodada_Zezo_Potiguar_Luan_Estilizado_B.m4a"},
    {"id":574,"artist":"Orlando Dias","title":"Tenho Ciúme de Tudo","genero":"BREGA","src":"Orlando_Dias_Orlando_Dias_Tenho_Ciume_De_Tudo_B.m4a"},
    {"id":575,"artist":"Os Dez Mandamentos","title":"Os Dez Mandamentos do Amor","genero":"BREGA","src":"Os_Dez_Os_Dez_Mandamentos_do_Amor_B.m4a"},
    {"id":576,"artist":"Osvaldo Oliveira","title":"Eu Acho Pouco","genero":"BREGA","src":"Osvaldo_Oliveira_Eu_Acho_Pouco_B.m4a"},
    {"id":577,"artist":"Avontade","title":"Outra Vida","genero":"BREGA","src":"Outra_Vida_Avontade.m4a"},
    {"id":578,"artist":"Perfume de Gardênia","title":"Perfume de Gardênia","genero":"BREGA","src":"Perfume_de_Perfume_de_Gardenia_B.m4a"},
    {"id":579,"artist":"Amado Batista","title":"Princesa","genero":"BREGA","src":"Princesa_AMADO-BATISTA-BREGA.m4a"},
    {"id":580,"artist":"Raimundo Soldado","title":"Minha Garota","genero":"BREGA","src":"Raimundo_Soldado_Minha_Garota_B.m4a"},
    {"id":581,"artist":"Roberto Carlos","title":"Furdúncio","genero":"BREGA","src":"Roberto_Carlos_Furduncio-B.m4a"},
    {"id":582,"artist":"José Ribeiro","title":"S Castigo","genero":"BREGA","src":"S_Castigo_JOSE-RIBEIRO-B.m4a"},
    {"id":583,"artist":"Uni","title":"Se Errar Outra Vez","genero":"BREGA","src":"Se_Errar_Se_Errar_Outra_Vez_UNI-B.m4a"},
    {"id":584,"artist":"Nival Santos","title":"Sendo Assim","genero":"BREGA","src":"Sendo_Assim_GEB-NIVAL-SANTOS-B.m4a"},
    {"id":585,"artist":"Fernando Mendes","title":"Sem Você","genero":"BREGA","src":"Sem_Voc_Sem_Voc_FERMENDO-MENDEB.m4a"},
    {"id":586,"artist":"José Ribeiro","title":"Serejeira Rosa","genero":"BREGA","src":"Serejeira_Rosa_JOSE-RIBEIRO-B.m4a"},
    {"id":587,"artist":"Siboney feat. Alcymar Monteiro","title":"Siboney","genero":"BREGA","src":"Siboney_feat_Siboney_feat_Alcymar_Monteiro-B.m4a"},
    {"id":588,"artist":"Bartô Gal","title":"Saudade de Rosa","genero":"BREGA","src":"SSaudade_de_Rosa-BARTO-GAL-B.m4a"},
    {"id":589,"artist":"Roberto Muller","title":"Te Responderei","genero":"BREGA","src":"Te_Responderei_ROBERTO-MULER-B.m4a"},
    {"id":590,"artist":"Vida pelo Avesso","title":"Vida Pelo Avesso","genero":"BREGA","src":"VIDA_PELO_VIDA_PELO_AVESSO_B.m4a"},
    {"id":591,"artist":"Lostalgia","title":"Você Não Me Ensinou a Te Esquecer","genero":"BREGA","src":"Voc_nao_me_ensinou_a_te_esquecer_Lostalgia_B.m4a"},
    {"id":592,"artist":"Waldik Soriano","title":"Um Homem Chora de Paixão","genero":"BREGA","src":"Waldik_Soriano_Um_Homem_Chora_De_Paix_B.m4a"},
  